itk/Configuration/Thickness3DConfig.py
itk/Configuration/Thickness3D_snake_case.py
itk/Thickness3DPython.py
itk/_Thickness3DPython.so
itk/itkThickness3DPython.py
itk_thickness3d-6.0.0.dist-info/METADATA
itk_thickness3d-6.0.0.dist-info/WHEEL
itk_thickness3d-6.0.0.dist-info/entry_points.txt
itk_thickness3d-6.0.0.dist-info/licenses/LICENSE
itk_thickness3d-6.0.0.dist-info/RECORD
